{
    "patches": [
        {
            "label": "2026-04-06_11-24-57",
            "content": "@@ -1094,30 +1094,16 @@\n i-1%5D %3C 0\n- && vet%5Bi%5D %3E 0\n %0A%09%09md :=\n@@ -1139,22 +1139,8 @@\n  %3C 0\n- && vet%5Bi%5D %3E 0\n %0A%0A%09%09\n",
            "lines": "244"
        },
        {
            "label": "2026-04-06_13-46-14",
            "content": "@@ -31,64 +31,64 @@\n %22%0A%09%22\n-cmp\n+fmt\n %22%0A%09%22\n-fmt\n+os\n %22%0A%09%22\n-math%22%0A%09%22os%22%0A%09%22slices%22%0A%09%22strconv%22%0A%09%22strings\n+strconv%22%0A%09%22strings%22%0A%09%22slices%22%0A%09%22cmp%22%0A%09%22math\n %22%0A)%0A\n@@ -1404,38 +1404,24 @@\n vet%5Bi-1%5D %3C 0\n- && vet%5Bi%5D %3E 0\n %0A%09%09md := i %3C\n@@ -1445,38 +1445,24 @@\n vet%5Bi+1%5D %3C 0\n- && vet%5Bi%5D %3E 0\n %0A%0A%09%09if !(me \n",
            "lines": "244"
        },
        {
            "label": "2026-04-06_13-51-52",
            "content": "@@ -1408,16 +1408,30 @@\n i-1%5D %3C 0\n+ && vet%5Bi%5D %3E 0\n %0A%09%09md :=\n@@ -1463,16 +1463,30 @@\n i+1%5D %3C 0\n+ && vet%5Bi%5D %3E 0\n %0A%0A%09%09if !\n@@ -1502,28 +1502,8 @@\n ) %7B%0A\n-%09%09%09if vet%5Bi%5D %3E 0 %7B%0A%09\n %09%09%09m\n@@ -1513,21 +1513,16 @@\n %5Bi%5D = 1%0A\n-%09%09%09%7D%0A\n %09%09%7D%0A%09%7D%0A%0A\n",
            "lines": "244"
        },
        {
            "label": "2026-04-06_14-02-42",
            "content": "@@ -2024,99 +2024,8 @@\n %09%09%7D%0A\n-%09%09%7Delse if elemento == seq%5Bcont - 1%5D %7B%0A%09%09%09id++%0A%09%09%09if cont == len(seq) %7B%0A%09%09%09%09return id%0A%09%09%09%7D%0A\n %09%09%7De\n",
            "lines": "246"
        },
        {
            "label": "2026-04-06_14-21-46",
            "content": "@@ -36,16 +36,8 @@\n mp%22%0A\n-%09%22flag%22%0A\n %09%22fm\n@@ -1890,204 +1890,309 @@\n  %7B%0A%09\n-%0A%09for i := 0; i %3C len(vet); i++ %7B%0A%09%09if vet%5Bi%5D == seq%5B0%5D%7B%0A%09%09%09j := i%0A%09%09%09flag := true%0A%09%09%09for _, verif := range seq %7B%0A%09%09%09%09if verif != vet%5Bj%5D%7B%0A%09%09%09%09%09flag = false%0A%09\n+cont := 0%0A%09id := 0%0A%09for i, elemento := range vet %7B%0A%09%09if elemento == seq%5Bcont%5D %7B%0A%09%09%09cont++%0A%09%09%09if cont == len(seq) %7B%0A%09%09%09%09return id%0A%09%09%09%7D%0A%09%09%7Delse if elemento == seq%5Bcont - 1%5D %7B%0A%09%09%09id++%0A%09%09%09if cont == len(seq) %7B%0A\n %09%09%09%09\n-b\n re\n-ak%0A%09%09%09%09%7D%0A%09%09%09%09j++%0A%09%09%09%7D%0A%09%09%09if flag\n+turn id%0A%09%09%09%7D%0A%09%09%7Delse if elemento == seq%5B0%5D %7B%0A%09%09%09cont = 1%0A%09%09%09id = i%0A%09%09%09if cont == len(seq)\n  %7B%0A%09\n@@ -2202,16 +2202,17 @@\n return i\n+d\n %0A%09%09%09%7D%0A%09%09\n@@ -2208,27 +2208,58 @@\n  id%0A%09%09%09%7D%0A%09%09%7D\n-%0A%09%09\n+else %7B%0A%09%09%09id = i+1%0A%09%09%09cont = 0%0A%09%09%7D\n %0A%09%7D%0A%09return \n",
            "lines": "251"
        },
        {
            "label": "2026-04-06_14-42-57",
            "content": "@@ -1964,19 +1964,20 @@\n := i%0A%09%09%09\n-aux\n+flag\n  := true\n@@ -2037,19 +2037,20 @@\n %5D%7B%0A%09%09%09%09%09\n-aux\n+flag\n  = false\n@@ -2086,19 +2086,20 @@\n %7D%0A%09%09%09if \n-aux\n+flag\n  %7B%0A%09%09%09%09r\n",
            "lines": "246"
        },
        {
            "label": "2026-04-06_14-43-38",
            "content": "@@ -32,16 +32,24 @@\n %0A%09%22cmp%22%0A\n+%09%22flag%22%0A\n %09%22fmt%22%0A%09\n",
            "lines": "246"
        },
        {
            "label": "2026-04-06_14-43-58",
            "content": "@@ -1957,40 +1957,8 @@\n = i%0A\n-%09%09%09if j %3E= len(vet) %7Breturn -1%7D%0A\n %09%09%09a\n",
            "lines": "245"
        },
        {
            "label": "2026-04-06_14-47-13",
            "content": "@@ -1890,48 +1890,8 @@\n  %7B%0A%09\n-if len(vet) %3C len(seq) %7B%0A%09%09return -1%0A%09%7D%0A\n %0A%09fo\n@@ -1916,27 +1916,16 @@\n vet)\n- - len(seq)\n ; i++ %7B%0A\n %09%09%0A%09\n@@ -1920,19 +1920,16 @@\n ; i++ %7B%0A\n-%09%09%0A\n %09%09if vet\n@@ -1953,16 +1953,48 @@\n %09j := i%0A\n+%09%09%09if j %3E= len(vet) %7Breturn -1%7D%0A\n %09%09%09aux :\n",
            "lines": "246"
        },
        {
            "label": "2026-04-06_14-53-45",
            "content": "@@ -1943,17 +1943,16 @@\n = 0; i %3C\n-=\n  len(vet\n",
            "lines": "249"
        },
        {
            "label": "2026-04-06_14-59-42",
            "content": "package main\n\nimport (\n\t\"bufio\"\n\t\"cmp\"\n\t\"fmt\"\n\t\"math\"\n\t\"os\"\n\t\"slices\"\n\t\"strconv\"\n\t\"strings\"\n)\n\ntype Pair struct {\n\tOne int\n\tTwo int\n}\n\nfunc occurr(vet []int) []Pair {\n\toccur := make([]Pair, 0, len(vet))\n\telementos := make(map[int]int)\n\t\n\tfor _, elemento := range vet {\n\t\telemento = int(math.Abs(float64(elemento)))\n\t\tif elementos[elemento] == 0 {\n\t\t\telementos[elemento] = 1\n\t\t}else {\n\t\t\telementos[elemento] += 1\n\t\t}\n\t}\n\tfor key, valor := range elementos {\n\t\toccur = append(occur, Pair{One: key, Two: valor})\n\t}\n\n\tslices.SortFunc(occur, func(a, b Pair) int { return cmp.Compare(a.One, b.One)})\n\treturn occur\n}\n\nfunc teams(vet []int) []Pair {\n\tif len(vet) == 0 {\n\t\treturn []Pair{} \n\t}\n\n\tteam := make([]Pair, 0, len(vet))\n\tvalor := vet[0]\n\trep := 1\n\n\tfor i := 1; i < len(vet); i++ {\n\n\t\tif vet[i] == valor {\n\t\t\trep++\n\n\t\t} else {\n\t\t\tteam = append(team, Pair{One: valor, Two: rep})\n\t\t\tvalor = vet[i]\n\t\t\trep = 1\n\t\t}\n\t}\n\n\tteam = append(team, Pair{One: valor, Two: rep})\n\treturn team\n}\n\nfunc mnext(vet []int) []int {\n\tmapa := make([]int,len(vet))\n\n\tfor i := 0; i < len(vet); i++ {\n\t\tme := i > 0 && vet[i-1] < 0 && vet[i] > 0\n\t\tmd := i < len(vet) - 1 && vet[i+1] < 0 && vet[i] > 0\n\n\t\tif me || md {\n\t\t\tmapa[i] = 1\n\t\t}\n\t}\n\n\treturn mapa\n}\n\nfunc alone(vet []int) []int {\n\tmapa := make([]int,len(vet))\n\tif len(vet) == 1 && vet[0] > 0 {\n\t\tmapa[0] = 1\n\t\treturn mapa\n\t}\n\n\tfor i := 0; i < len(vet); i++ {\n\t\tme := i > 0 && vet[i-1] < 0\n\t\tmd := i < len(vet) - 1 && vet[i+1] < 0\n\n\t\tif !(me || md) {\n\t\t\tif vet[i] > 0 {\n\t\t\t\tmapa[i] = 1\n\t\t\t}\n\t\t}\n\t}\n\n\treturn mapa\n}\n\nfunc couple(vet []int) int {\n\t\n\tsolt := make(map[int]int)\n\tcont := 0\n\tfor _, elemento := range vet {\n\t\tif solt[-elemento] > 0 {\n\t\t\tcont ++\n\t\t\tsolt[-elemento]--\n\t\t}else {\n\t\t\tsolt[elemento]++\n\t\t}\n\t}\n\n\treturn cont\n}\n\nfunc hasSubseq(vet []int, seq []int, pos int) bool {\n\t_ = vet\n\t_ = seq\n\t_ = pos\n\treturn false\n}\n\nfunc subseq(vet []int, seq []int) int {\n\tif len(vet) < len(seq) {\n\t\treturn -1\n\t}\n\n\tfor i := 0; i <= len(vet) - len(seq); i++ {\n\t\t\n\t\tif vet[i] == seq[0]{\n\t\t\tj := i\n\t\t\taux := true\n\t\t\tfor _, verif := range seq {\n\t\t\t\tif verif != vet[j]{\n\t\t\t\t\taux = false\n\t\t\t\t\tbreak\n\t\t\t\t}\n\t\t\t\tj++\n\t\t\t}\n\t\t\tif aux {\n\t\t\t\treturn i\n\t\t\t}\n\t\t}\n\t\t\n\t}\n\treturn -1\n}\n\nfunc erase(vet []int, posList []int) []int {\n\n\tmapa := make(map[int]bool, len(posList))\n\tsize := len(vet) - len(posList)\n\tnewList := make([]int, 0, size)\n\n\tif size == 0 { return newList}\n\n\tfor _, id := range posList {\n\t\tmapa[id] = true\n\t}\n\t\n\tfor i, elemento := range vet {\n\t\tif !mapa[i] {\n\t\t\tnewList = append(newList, elemento)\n\t\t}\n\t}\n\n\treturn newList\n}\n\nfunc clear(vet []int, value int) []int {\n\n\tnewList := make([]int, 0, len(vet))\n\t\n\tfor _, elemento := range vet {\n\t\tif elemento != value {\n\t\t\tnewList = append(newList, elemento)\n\t\t}\n\t\t\n\t}\n\treturn newList\n}\n\nfunc main() {\n\tscanner := bufio.NewScanner(os.Stdin)\n\tfor {\n\t\tfmt.Print(\"$\")\n\t\tif !scanner.Scan() {\n\t\t\tbreak\n\t\t}\n\t\tline := scanner.Text()\n\t\targs := strings.Split(line, \" \")\n\t\tfmt.Println(line)\n\n\t\tswitch args[0] {\n\t\tcase \"occurr\":\n\t\t\tprintSlice(occurr(str2vet(args[1])))\n\t\tcase \"teams\":\n\t\t\tprintSlice(teams(str2vet(args[1])))\n\t\tcase \"mnext\":\n\t\t\tprintSlice(mnext(str2vet(args[1])))\n\t\tcase \"alone\":\n\t\t\tprintSlice(alone(str2vet(args[1])))\n\t\tcase \"erase\":\n\t\t\tprintSlice(erase(str2vet(args[1]), str2vet(args[2])))\n\t\tcase \"clear\":\n\t\t\tval, _ := strconv.Atoi(args[2])\n\t\t\tprintSlice(clear(str2vet(args[1]), val))\n\t\tcase \"subseq\":\n\t\t\tfmt.Println(subseq(str2vet(args[1]), str2vet(args[2])))\n\t\tcase \"couple\":\n\t\t\tfmt.Println(couple(str2vet(args[1])))\n\t\tcase \"end\":\n\t\t\treturn\n\t\tdefault:\n\t\t\tfmt.Println(\"Invalid command\")\n\t\t}\n\t}\n}\n\n// Fun\u00e7\u00f5es auxiliares\n\nfunc str2vet(str string) []int {\n\tif str == \"[]\" {\n\t\treturn nil\n\t}\n\tstr = str[1 : len(str)-1]\n\tparts := strings.Split(str, \",\")\n\tvar vet []int\n\tfor _, part := range parts {\n\t\tnum, _ := strconv.Atoi(strings.TrimSpace(part))\n\t\tvet = append(vet, num)\n\t}\n\treturn vet\n}\n\nfunc printSlice[T any](vet []T) {\n\tfmt.Print(\"[\")\n\tfor i, x := range vet {\n\t\tif i > 0 {\n\t\t\tfmt.Print(\", \")\n\t\t}\n\t\tfmt.Print(x)\n\t}\n\tfmt.Println(\"]\")\n}\n\nfunc (p Pair) String() string {\n\treturn fmt.Sprintf(\"(%v, %v)\", p.One, p.Two)\n}\n",
            "lines": "249"
        }
    ]
}