{
    "patches": [
        {
            "label": "2026-04-03_14-51-34",
            "content": "package main\n\nimport (\n\t\"bufio\"\n\t\"fmt\"\n\t\"os\"\n\t\"strconv\"\n\t\"strings\"\n\t\"slices\"\n\t\"math\"\n\t\"cmp\"\n)\n\nfunc getMen(vet []int) []int {\n\tmen := make([]int, 0, len(vet))\n\n\tfor _, pessoa := range vet {\n\t\tif pessoa > 0 {\n\t\t\tmen = append(men, pessoa)\n\t\t}\n\t}\n\treturn men\n}\n\nfunc getCalmWomen(vet []int) []int {\n\twomen := make([]int, 0, len(vet))\n\n\tfor _, pessoa := range vet {\n\t\tif pessoa < 0 && pessoa > -10{\n\t\t\twomen = append(women, pessoa)\n\t\t}\n\t}\n\treturn women\n}\n\nfunc sortVet(vet []int) []int {\n\tslices.Sort(vet)\n\treturn vet\n}\n\nfunc sortStress(vet []int) []int {\n\tslices.SortFunc(vet, func(a, b int) int {\n\t\treturn cmp.Compare(math.Abs(float64(a)), math.Abs(float64(b)))\n\t})\n\treturn vet\n}\n\nfunc reverse(vet []int) []int {\n\tvetR := make([]int, len(vet))\n\tcopy(vetR, vet)\n\tslices.Reverse(vetR)\n\n\treturn vetR\n}\n\nfunc unique(vet []int) []int {\n\telementos := make(map[int]bool)\n\tvetU := make([]int, 0, len(vet))\n\n\tfor _, elemento := range vet {\n\t\tif !elementos[elemento] {\n\t\t\tvetU = append(vetU, elemento)\n\t\t\telementos[elemento] = true\n\t\t}\n\t}\n\n\treturn vetU\n}\n\nfunc repeated(vet []int) []int {\n\telementos := make(map[int]bool)\n\tvetR := make([]int, 0, len(vet))\n\n\tfor _, elemento := range vet {\n\t\tif elementos[elemento] {\n\t\t\tvetR = append(vetR, elemento)\n\t\t}else {\n\t\t\telementos[elemento] = true\n\t\t}\n\t}\n\n\treturn vetR\n}\n\nfunc main() {\n\tscanner := bufio.NewScanner(os.Stdin)\n\n\tfor {\n\t\tif !scanner.Scan() {\n\t\t\tbreak\n\t\t}\n\t\tfmt.Print(\"$\")\n\t\tline := scanner.Text()\n\t\targs := strings.Split(line, \" \")\n\t\tfmt.Println(line)\n\n\t\tswitch args[0] {\n\t\tcase \"get_men\":\n\t\t\tprintVec(getMen(str2vet(args[1])))\n\t\tcase \"get_calm_women\":\n\t\t\tprintVec(getCalmWomen(str2vet(args[1])))\n\t\tcase \"sort\":\n\t\t\tprintVec(sortVet(str2vet(args[1])))\n\t\tcase \"sort_stress\":\n\t\t\tprintVec(sortStress(str2vet(args[1])))\n\t\tcase \"reverse\":\n\t\t\tarray := str2vet(args[1])\n\t\t\tother := reverse(array)\n\t\t\tprintVec(array)\n\t\t\tprintVec(other)\n\t\tcase \"unique\":\n\t\t\tprintVec(unique(str2vet(args[1])))\n\t\tcase \"repeated\":\n\t\t\tprintVec(repeated(str2vet(args[1])))\n\t\tcase \"end\":\n\t\t\treturn\n\t\t}\n\t}\n}\n\nfunc printVec(vet []int) {\n\tfmt.Print(\"[\")\n\tfor i, val := range vet {\n\t\tif i > 0 {\n\t\t\tfmt.Print(\", \")\n\t\t}\n\t\tfmt.Print(val)\n\t}\n\tfmt.Println(\"]\")\n}\n\nfunc str2vet(s string) []int {\n\tif s == \"[]\" {\n\t\treturn nil\n\t}\n\ts = s[1 : len(s)-1]\n\tparts := strings.Split(s, \",\")\n\tvar vet []int\n\tfor _, part := range parts {\n\t\tn, _ := strconv.Atoi(part)\n\t\tvet = append(vet, n)\n\t}\n\treturn vet\n}\n\n",
            "lines": "145"
        }
    ]
}